README.md
setup.py
lxc/__init__.py
lxc/camera_op.py
lxc/file_op.py
lxc/image_op.py
lxc/json_op.py
lxc/las_2_octree.py
lxc/pcd_2_las.py
lxc/str_op.py
lxc/game/__init__.py
lxc/game/cmd_2048.py
lxc/game/cmd_minesweeping.py
lxc/game/cmd_snake.py
lxc_sdk.egg-info/PKG-INFO
lxc_sdk.egg-info/SOURCES.txt
lxc_sdk.egg-info/dependency_links.txt
lxc_sdk.egg-info/requires.txt
lxc_sdk.egg-info/top_level.txt