Metadata-Version: 2.1
Name: lxc-sdk
Version: 0.2.1
Summary: Tools for convenient developing <3
Home-page: UNKNOWN
Author: Starlight
Author-email: darkbug11@foxmail.com
License: UNKNOWN
Platform: UNKNOWN
Classifier: Programming Language :: Python :: 3
Classifier: License :: OSI Approved :: MIT License
Classifier: Operating System :: OS Independent
Requires-Python: >=3.6
